Shynasysinfo/Shsysinfo.py
Shynasysinfo/__init__.py
ShynaSystemInfo-0.4.dist-info/LICENSE
ShynaSystemInfo-0.4.dist-info/METADATA
ShynaSystemInfo-0.4.dist-info/WHEEL
ShynaSystemInfo-0.4.dist-info/top_level.txt
ShynaSystemInfo-0.4.dist-info/RECORD
