Metadata-Version: 2.1
Name: ShynaSystemInfo
Version: 0.4
Summary: Shyna Backend Functionality Package to fetch System information
Home-page: UNKNOWN
Author: Shivam Sharma
Author-email: shivamsharma1913@gmail.com
License: UNKNOWN
Platform: UNKNOWN
License-File: LICENSE
Requires-Dist: psutil
Requires-Dist: setuptools
Requires-Dist: wheel
Requires-Dist: urllib3
Requires-Dist: tabulate
Requires-Dist: GPUtil
